{
    "image_id": "60009710.jpg",
    "file_path": "/home/user/myLearning/OCR_Project/processed_image/60009710.jpg",
    "summary": "The image is a document titled \"ex convoy\" addressed to Mr. Paul A., Pandour Senior Vice President & general Counsel of The American Tobacco Company. It requests payment in the amount of $158,632.00 for 1985 dues and mentions that without this payment, the Council's General Fund will be insufficient. The check should be made out to THE COUNCIL FOR TOBACCO RESEARCH-US.A., INC., and it advises that if not paid in full by 1986, interest at 15% per annum will accrue on any unpaid balance. The document is signed by Fans Gstory, Treasurer.",
    "corrected_text": "ex convoy For tobacco RuszarcH~.S.A., Inc, 000,4HIRD AVENUE NEW YORK, NY, 10022. March 20, 1986 Mr. Paul A, pandour Senior Vice President & general Counsel The American Tobacco Company. 245 Park Avenue New York, N 10167 Dear Mr. Randour: Cash requirements make it necessary for The Council t replenish its General Fund. Will you please, therefore, return a check to this office for $158,632.00, representing your Company's tenth and eleventh installments of 1985 dues. This payment will bring the total unpaid balance to be paid by your Company, on 1985 dues to $79,312.71. The check should be made out to THE COUNCIL FOR TOBACCO RESEARCH-US.A,, INC. Sincerely, Fans G story Treasurer BGS/Ip get Thomas:C. Hays Janet C: Brown, Esa. (leo individually addressed to: Peterson (Ave;Stevens) ; pullman (Ahrensfetd, Holtzman); wit (Di Marco); battle (Manning, Chapin). pt Sees Sea can aka can air",
    "ner": [
        [
            "Inc",
            "ORG"
        ],
        [
            "AVENUE",
            "ORG"
        ],
        [
            "NEW YORK",
            "GPE"
        ],
        [
            "NY",
            "GPE"
        ],
        [
            "10022",
            "DATE"
        ],
        [
            "March 20, 1986",
            "DATE"
        ],
        [
            "Paul A",
            "PERSON"
        ],
        [
            "Counsel The American Tobacco Company",
            "ORG"
        ],
        [
            "245",
            "CARDINAL"
        ],
        [
            "Park Avenue",
            "FAC"
        ],
        [
            "New York",
            "GPE"
        ],
        [
            "Randour",
            "PERSON"
        ],
        [
            "Council",
            "ORG"
        ],
        [
            "General Fund",
            "ORG"
        ],
        [
            "158,632.00",
            "MONEY"
        ],
        [
            "tenth",
            "ORDINAL"
        ],
        [
            "eleventh",
            "ORDINAL"
        ],
        [
            "1985",
            "DATE"
        ],
        [
            "1985",
            "DATE"
        ],
        [
            "79,312.71",
            "MONEY"
        ],
        [
            "THE COUNCIL FOR TOBACCO RESEARCH-US.A",
            "ORG"
        ],
        [
            "Fans",
            "NORP"
        ],
        [
            "Thomas",
            "PERSON"
        ],
        [
            "leo",
            "ORG"
        ],
        [
            "Peterson",
            "PERSON"
        ],
        [
            "Ahrensfetd, Holtzman",
            "ORG"
        ],
        [
            "Di Marco",
            "PERSON"
        ],
        [
            "Chapin",
            "GPE"
        ]
    ],
    "pos_tags": [
        [
            "ex",
            "PROPN"
        ],
        [
            "convoy",
            "NOUN"
        ],
        [
            "For",
            "ADP"
        ],
        [
            "tobacco",
            "NOUN"
        ],
        [
            "RuszarcH~.S.A.",
            "PROPN"
        ],
        [
            ",",
            "PUNCT"
        ],
        [
            "Inc",
            "PROPN"
        ],
        [
            ",",
            "PUNCT"
        ],
        [
            "000,4HIRD",
            "PUNCT"
        ],
        [
            "AVENUE",
            "PROPN"
        ],
        [
            "NEW",
            "PROPN"
        ],
        [
            "YORK",
            "PROPN"
        ],
        [
            ",",
            "PUNCT"
        ],
        [
            "NY",
            "PROPN"
        ],
        [
            ",",
            "PUNCT"
        ],
        [
            "10022",
            "NUM"
        ],
        [
            ".",
            "PUNCT"
        ],
        [
            "March",
            "PROPN"
        ],
        [
            "20",
            "NUM"
        ],
        [
            ",",
            "PUNCT"
        ],
        [
            "1986",
            "NUM"
        ],
        [
            "Mr.",
            "PROPN"
        ],
        [
            "Paul",
            "PROPN"
        ],
        [
            "A",
            "PROPN"
        ],
        [
            ",",
            "PUNCT"
        ],
        [
            "pandour",
            "NOUN"
        ],
        [
            "Senior",
            "PROPN"
        ],
        [
            "Vice",
            "PROPN"
        ],
        [
            "President",
            "PROPN"
        ],
        [
            "&",
            "CCONJ"
        ],
        [
            "general",
            "PROPN"
        ],
        [
            "Counsel",
            "PROPN"
        ],
        [
            "The",
            "DET"
        ],
        [
            "American",
            "PROPN"
        ],
        [
            "Tobacco",
            "PROPN"
        ],
        [
            "Company",
            "PROPN"
        ],
        [
            ".",
            "PUNCT"
        ],
        [
            "245",
            "NUM"
        ],
        [
            "Park",
            "PROPN"
        ],
        [
            "Avenue",
            "PROPN"
        ],
        [
            "New",
            "PROPN"
        ],
        [
            "York",
            "PROPN"
        ],
        [
            ",",
            "PUNCT"
        ],
        [
            "N",
            "PROPN"
        ],
        [
            "10167",
            "NUM"
        ],
        [
            "Dear",
            "PROPN"
        ],
        [
            "Mr.",
            "PROPN"
        ],
        [
            "Randour",
            "PROPN"
        ],
        [
            ":",
            "PUNCT"
        ],
        [
            "Cash",
            "NOUN"
        ],
        [
            "requirements",
            "NOUN"
        ],
        [
            "make",
            "VERB"
        ],
        [
            "it",
            "PRON"
        ],
        [
            "necessary",
            "ADJ"
        ],
        [
            "for",
            "SCONJ"
        ],
        [
            "The",
            "DET"
        ],
        [
            "Council",
            "PROPN"
        ],
        [
            "t",
            "NOUN"
        ],
        [
            "replenish",
            "VERB"
        ],
        [
            "its",
            "PRON"
        ],
        [
            "General",
            "PROPN"
        ],
        [
            "Fund",
            "PROPN"
        ],
        [
            ".",
            "PUNCT"
        ],
        [
            "Will",
            "AUX"
        ],
        [
            "you",
            "PRON"
        ],
        [
            "please",
            "VERB"
        ],
        [
            ",",
            "PUNCT"
        ],
        [
            "therefore",
            "ADV"
        ],
        [
            ",",
            "PUNCT"
        ],
        [
            "return",
            "VERB"
        ],
        [
            "a",
            "DET"
        ],
        [
            "check",
            "NOUN"
        ],
        [
            "to",
            "ADP"
        ],
        [
            "this",
            "DET"
        ],
        [
            "office",
            "NOUN"
        ],
        [
            "for",
            "ADP"
        ],
        [
            "$",
            "SYM"
        ],
        [
            "158,632.00",
            "NUM"
        ],
        [
            ",",
            "PUNCT"
        ],
        [
            "representing",
            "VERB"
        ],
        [
            "your",
            "PRON"
        ],
        [
            "Company",
            "NOUN"
        ],
        [
            "'s",
            "PART"
        ],
        [
            "tenth",
            "ADJ"
        ],
        [
            "and",
            "CCONJ"
        ],
        [
            "eleventh",
            "ADJ"
        ],
        [
            "installments",
            "NOUN"
        ],
        [
            "of",
            "ADP"
        ],
        [
            "1985",
            "NUM"
        ],
        [
            "dues",
            "NOUN"
        ],
        [
            ".",
            "PUNCT"
        ],
        [
            "This",
            "DET"
        ],
        [
            "payment",
            "NOUN"
        ],
        [
            "will",
            "AUX"
        ],
        [
            "bring",
            "VERB"
        ],
        [
            "the",
            "DET"
        ],
        [
            "total",
            "ADJ"
        ],
        [
            "unpaid",
            "ADJ"
        ],
        [
            "balance",
            "NOUN"
        ],
        [
            "to",
            "PART"
        ],
        [
            "be",
            "AUX"
        ],
        [
            "paid",
            "VERB"
        ],
        [
            "by",
            "ADP"
        ],
        [
            "your",
            "PRON"
        ],
        [
            "Company",
            "PROPN"
        ],
        [
            ",",
            "PUNCT"
        ],
        [
            "on",
            "ADP"
        ],
        [
            "1985",
            "NUM"
        ],
        [
            "dues",
            "NOUN"
        ],
        [
            "to",
            "ADP"
        ],
        [
            "$",
            "SYM"
        ],
        [
            "79,312.71",
            "NOUN"
        ],
        [
            ".",
            "PUNCT"
        ],
        [
            "The",
            "DET"
        ],
        [
            "check",
            "NOUN"
        ],
        [
            "should",
            "AUX"
        ],
        [
            "be",
            "AUX"
        ],
        [
            "made",
            "VERB"
        ],
        [
            "out",
            "ADP"
        ],
        [
            "to",
            "ADP"
        ],
        [
            "THE",
            "DET"
        ],
        [
            "COUNCIL",
            "PROPN"
        ],
        [
            "FOR",
            "ADP"
        ],
        [
            "TOBACCO",
            "PROPN"
        ],
        [
            "RESEARCH",
            "PROPN"
        ],
        [
            "-",
            "PUNCT"
        ],
        [
            "US.A",
            "PROPN"
        ],
        [
            ",",
            "PUNCT"
        ],
        [
            ",",
            "PUNCT"
        ],
        [
            "INC",
            "PROPN"
        ],
        [
            ".",
            "PUNCT"
        ],
        [
            "Sincerely",
            "ADV"
        ],
        [
            ",",
            "PUNCT"
        ],
        [
            "Fans",
            "PROPN"
        ],
        [
            "G",
            "NOUN"
        ],
        [
            "story",
            "NOUN"
        ],
        [
            "Treasurer",
            "PROPN"
        ],
        [
            "BGS",
            "PROPN"
        ],
        [
            "/",
            "PUNCT"
        ],
        [
            "Ip",
            "PRON"
        ],
        [
            "get",
            "VERB"
        ],
        [
            "Thomas",
            "PROPN"
        ],
        [
            ":",
            "PUNCT"
        ],
        [
            "C.",
            "PROPN"
        ],
        [
            "Hays",
            "NOUN"
        ],
        [
            "Janet",
            "PROPN"
        ],
        [
            "C",
            "PROPN"
        ],
        [
            ":",
            "PUNCT"
        ],
        [
            "Brown",
            "PROPN"
        ],
        [
            ",",
            "PUNCT"
        ],
        [
            "Esa",
            "PROPN"
        ],
        [
            ".",
            "PUNCT"
        ],
        [
            "(",
            "PUNCT"
        ],
        [
            "leo",
            "PROPN"
        ],
        [
            "individually",
            "ADV"
        ],
        [
            "addressed",
            "VERB"
        ],
        [
            "to",
            "ADP"
        ],
        [
            ":",
            "PUNCT"
        ],
        [
            "Peterson",
            "PROPN"
        ],
        [
            "(",
            "PUNCT"
        ],
        [
            "Ave;Stevens",
            "PROPN"
        ],
        [
            ")",
            "PUNCT"
        ],
        [
            ";",
            "PUNCT"
        ],
        [
            "pullman",
            "NOUN"
        ],
        [
            "(",
            "PUNCT"
        ],
        [
            "Ahrensfetd",
            "PROPN"
        ],
        [
            ",",
            "PUNCT"
        ],
        [
            "Holtzman",
            "PROPN"
        ],
        [
            ")",
            "PUNCT"
        ],
        [
            ";",
            "PUNCT"
        ],
        [
            "wit",
            "NOUN"
        ],
        [
            "(",
            "PUNCT"
        ],
        [
            "Di",
            "PROPN"
        ],
        [
            "Marco",
            "PROPN"
        ],
        [
            ")",
            "PUNCT"
        ],
        [
            ";",
            "PUNCT"
        ],
        [
            "battle",
            "NOUN"
        ],
        [
            "(",
            "PUNCT"
        ],
        [
            "Manning",
            "PROPN"
        ],
        [
            ",",
            "PUNCT"
        ],
        [
            "Chapin",
            "PROPN"
        ],
        [
            ")",
            "PUNCT"
        ],
        [
            ".",
            "PUNCT"
        ],
        [
            "pt",
            "PROPN"
        ],
        [
            "Sees",
            "PROPN"
        ],
        [
            "Sea",
            "PROPN"
        ],
        [
            "can",
            "AUX"
        ],
        [
            "aka",
            "ADV"
        ],
        [
            "can",
            "AUX"
        ],
        [
            "air",
            "VERB"
        ]
    ]
}